replkit2/__init__.py
replkit2/app.py
replkit2/formatters.py
replkit2/llms.txt
replkit2/py.typed
replkit2/validation.py
replkit2/integrations/__init__.py
replkit2/integrations/cli.py
replkit2/integrations/mcp/__init__.py
replkit2/integrations/mcp/integration.py
replkit2/integrations/mcp/parameters.py
replkit2/integrations/mcp/prompts.py
replkit2/integrations/mcp/resources.py
replkit2/integrations/mcp/tools.py
replkit2/integrations/mcp/uri.py
replkit2/integrations/mcp/wrappers.py
replkit2/textkit/README.md
replkit2/textkit/__init__.py
replkit2/textkit/charts.py
replkit2/textkit/config.py
replkit2/textkit/core.py
replkit2/textkit/display.py
replkit2/textkit/formatter.py
replkit2/textkit/icons.py
replkit2/textkit/layout.py
replkit2/textkit/markdown/PLAN.md
replkit2/textkit/markdown/__init__.py
replkit2/textkit/markdown/alert.py
replkit2/textkit/markdown/base.py
replkit2/textkit/markdown/builder.py
replkit2/textkit/markdown/elements.py
replkit2/textkit/markdown/llms.txt
replkit2/textkit/markdown/table.py
replkit2/textkit/markdown/transforms.py
replkit2/types/__init__.py
replkit2/types/core.py
replkit2/types/display.py
replkit2-0.12.0.dist-info/METADATA
replkit2-0.12.0.dist-info/WHEEL
replkit2-0.12.0.dist-info/licenses/LICENSE
replkit2-0.12.0.dist-info/RECORD
