Metadata-Version: 2.4
Name: replkit2
Version: 0.12.0
Summary: A minimal Python framework for building stateful REPL applications with ASCII display
Project-URL: Repository, https://github.com/angelsen/replkit2
Project-URL: Issues, https://github.com/angelsen/replkit2/issues
Author-email: Fredrik Angelsen <fredrikangelsen@gmail.com>
License: MIT
License-File: LICENSE
Keywords: cli,framework,mcp,repl,stateful,terminal
Classifier: Development Status :: 4 - Beta
Classifier: License :: OSI Approved :: MIT License
Classifier: Programming Language :: Python :: 3.12
Requires-Python: >=3.12
Provides-Extra: all
Requires-Dist: fastmcp>=2.9.2; extra == 'all'
Requires-Dist: typer>=0.16.0; extra == 'all'
Provides-Extra: cli
Requires-Dist: typer>=0.16.0; extra == 'cli'
Provides-Extra: examples
Requires-Dist: fastapi>=0.116.1; extra == 'examples'
Requires-Dist: psutil>=7.0.0; extra == 'examples'
Requires-Dist: uvicorn>=0.35.0; extra == 'examples'
Provides-Extra: mcp
Requires-Dist: fastmcp>=2.9.2; extra == 'mcp'
